QiwiBillPaymentsAPI/QiwiBillPaymentsAPI.py
QiwiBillPaymentsAPI/__init__.py
qiwiBillPaymentsAPI-0.2.dist-info/METADATA
qiwiBillPaymentsAPI-0.2.dist-info/WHEEL
qiwiBillPaymentsAPI-0.2.dist-info/top_level.txt
qiwiBillPaymentsAPI-0.2.dist-info/RECORD
