Metadata-Version: 2.1
Name: qiwiBillPaymentsAPI
Version: 0.2
Summary: Qiwi Bill Payments API
Home-page: https://github.com/LucifierArchangel/QiwiBillPaymentsAPI
Author: LucifierArchangel
Author-email: lucifier.archangel@gmail.com
License: UNKNOWN
Platform: UNKNOWN
Classifier: Programming Language :: Python :: 3
Classifier: License :: OSI Approved :: MIT License
Classifier: Operating System :: OS Independent
Requires-Python: >=3.4
